horofns/utils.py
horofns-0.1.dist-info/DESCRIPTION.rst
horofns-0.1.dist-info/METADATA
horofns-0.1.dist-info/RECORD
horofns-0.1.dist-info/WHEEL
horofns-0.1.dist-info/metadata.json
horofns-0.1.dist-info/top_level.txt
