Metadata-Version: 2.0
Name: horofns
Version: 0.1
Summary: A Python utility package of Horo fns
Home-page: https://github.com/joelhoro
Author: Joel Horowitz
Author-email: joelhoro@gmail.com
License: UNKNOWN
Platform: UNKNOWN
Classifier: Programming Language :: Python :: 3
Classifier: License :: OSI Approved :: MIT License
Classifier: Operating System :: OS Independent
